.gitignore
HISTORY.TXT
LICENSE
MANIFEST.in
README.rst
bootstrap.py
buildout.cfg
setup.py
CodeSkel.egg-info/PKG-INFO
CodeSkel.egg-info/SOURCES.txt
CodeSkel.egg-info/dependency_links.txt
CodeSkel.egg-info/entry_points.txt
CodeSkel.egg-info/not-zip-safe
CodeSkel.egg-info/requires.txt
CodeSkel.egg-info/top_level.txt
codeskel/__init__.py
codeskel/base.py
codeskel/bootstrap_theme.py
codeskel/cs_django_buildout.py
codeskel/cs_django_project.py
codeskel/cs_plone3_theme.py
codeskel/cs_plone4_buildout.py
codeskel/cs_plone5_theme.py
codeskel/dexterity_cs.py
codeskel/localcommands/__init__.py
codeskel/localcommands/dexterity.py
codeskel/localcommands/templates/dexterity/content_cs/+content_class_filename+.py_tmpl
codeskel/localcommands/templates/dexterity/content_cs/content.zcml_insert
codeskel/localcommands/templates/dexterity/content_cs/permissions.zcml_insert
codeskel/localcommands/templates/dexterity/content_cs/profiles/default/diff_tool.xml_insert
codeskel/localcommands/templates/dexterity/content_cs/profiles/default/registry.xml_insert
codeskel/localcommands/templates/dexterity/content_cs/profiles/default/rolemap.xml_insert
codeskel/localcommands/templates/dexterity/content_cs/profiles/default/types.xml_insert
codeskel/localcommands/templates/dexterity/content_cs/profiles/default/types/+contenttype_name+.xml_tmpl
codeskel/localcommands/templates/dexterity/content_cs/templates/+content_class_filename+view.pt_tmpl
codeskel/templates/bootstrap_theme/+project+-configure.zcml_tmpl
codeskel/templates/bootstrap_theme/MANIFEST.in_tmpl
codeskel/templates/bootstrap_theme/ignore.txt
codeskel/templates/bootstrap_theme/setup.py_tmpl
codeskel/templates/bootstrap_theme/+namespace_package+/+package+/__init__.py_tmpl
codeskel/templates/bootstrap_theme/+namespace_package+/+package+/configure.zcml_tmpl
codeskel/templates/bootstrap_theme/+namespace_package+/+package+/profiles.zcml_tmpl
codeskel/templates/bootstrap_theme/+namespace_package+/+package+/rebuild_i18n.sh_tmpl
codeskel/templates/bootstrap_theme/+namespace_package+/+package+/setuphandlers.py_tmpl
codeskel/templates/bootstrap_theme/+namespace_package+/+package+/skins.zcml_tmpl
